genaikeys/__init__.py
genaikeys/_aws_secret_manager.py
genaikeys/_azure_keyvault.py
genaikeys/_gcp_secret_manager.py
genaikeys/_secret_manager_default.py
genaikeys/types.py
genaikeys-0.0.1rc2.dist-info/LICENSE
genaikeys-0.0.1rc2.dist-info/METADATA
genaikeys-0.0.1rc2.dist-info/WHEEL
genaikeys-0.0.1rc2.dist-info/RECORD
