Metadata-Version: 2.1
Name: genaikeys
Version: 0.0.1rc2
Summary: A convenient secret retrieval proxy backed by cloud scale secret vaults
Home-page: https://github.com/ndamulelonemakh/genaikeys
License: MIT
Keywords: secrets,AI,cloud,vault,security
Author: Ndamulelo Nemakhavhani
Author-email: ndamulelo@rihonegroup.com
Requires-Python: >=3.10,<4.0
Classifier: Intended Audience :: Developers
Classifier: License :: OSI Approved :: MIT License
Classifier: Operating System :: OS Independent
Classifier: Programming Language :: Python :: 3
Classifier: Programming Language :: Python :: 3.10
Classifier: Programming Language :: Python :: 3.11
Classifier: Programming Language :: Python :: 3.12
Classifier: Programming Language :: Python :: 3.13
Classifier: Topic :: Security
Provides-Extra: all
Provides-Extra: aws
Provides-Extra: gcp
Requires-Dist: azure-identity (>=1.17.1,<2.0.0)
Requires-Dist: azure-keyvault-secrets (>=4.8.0,<5.0.0)
Requires-Dist: cryptography (>=43.0.1,<44.0.0)
Project-URL: Repository, https://github.com/ndamulelonemakh/genaikeys
